isfilled
