Metadata-Version: 1.0
Name: isfilled
Version: 0.5
Summary: Filledness for Models and ModelForms
Home-page: http://github.com/futurice/isfilled
Author: Jussi Vaihia
Author-email: jussi.vaihia@futurice.com
License: BSD
Keywords: django form filled condition
Platform: UNKNOWN
